[{"date":"1689551392","open":0.0,"high":28.0,"low":27.0,"close":0.0},{"date":"1689552292","open":0.0,"high":28.0,"low":27.0,"close":0.0},{"date":"1689553192","open":0.0,"high":28.0,"low":27.0,"close":0.0},{"date":"1689554092","open":0.0,"high":28.0,"low":27.0,"close":0.0},{"date":"1689554992","open":0.0,"high":28.0,"low":27.0,"close":0.0},{"date":"1689555892","open":0.0,"high":28.0,"low":27.0,"close":0.0},{"date":"1689556792","open":0.0,"high":28.0,"low":27.0,"close":0.0},{"date":"1689557692","open":0.0,"high":28.0,"low":27.0,"close":0.0},{"date":"1689558592","open":0.0,"high":28.0,"low":27.0,"close":0.0},{"date":"1689559492","open":0.0,"high":28.0,"low":27.0,"close":0.0},{"date":"1689560392","open":0.0,"high":28.0,"low":27.0,"close":0.0},{"date":"1689561292","open":0.0,"high":28.0,"low":27.0,"close":0.0},{"date":"1689562192","open":0.0,"high":28.0,"low":27.0,"close":0.0},{"date":"1689563092","open":0.0,"high":28.0,"low":27.0,"close":0.0},{"date":"1689563992","open":0.0,"high":28.0,"low":27.0,"close":0.0},{"date":"1689564892","open":0.0,"high":28.0,"low":27.0,"close":0.0},{"date":"1689565792","open":0.0,"high":28.0,"low":27.0,"close":0.0},{"date":"1689566692","open":0.0,"high":28.0,"low":27.0,"close":0.0},{"date":"1689567592","open":0.0,"high":28.0,"low":27.0,"close":0.0},{"date":"1689568492","open":0.0,"high":28.0,"low":27.0,"close":0.0},{"date":"1689569392","open":0.0,"high":28.0,"low":27.0,"close":0.0},{"date":"1689570292","open":0.0,"high":28.0,"low":27.0,"close":0.0},{"date":"1689571192","open":0.0,"high":28.0,"low":27.0,"close":0.0},{"date":"1689572092","open":0.0,"high":28.0,"low":27.0,"close":0.0},{"date":"1689572992","open":0.0,"high":28.0,"low":27.0,"close":0.0},{"date":"1689573892","open":0.0,"high":28.0,"low":27.0,"close":0.0},{"date":"1689574792","open":0.0,"high":28.0,"low":27.0,"close":0.0},{"date":"1689575692","open":0.0,"high":28.0,"low":27.0,"close":0.0},{"date":"1689576592","open":0.0,"high":28.0,"low":27.0,"close":0.0},{"date":"1689577492","open":0.0,"high":28.0,"low":27.0,"close":0.0},{"date":"1689578392","open":0.0,"high":28.0,"low":28.0,"close":0.0},{"date":"1689579292","open":0.0,"high":28.0,"low":28.0,"close":0.0},{"date":"1689580192","open":0.0,"high":28.0,"low":28.0,"close":0.0},{"date":"1689581092","open":0.0,"high":29.0,"low":28.0,"close":0.0},{"date":"1689581992","open":0.0,"high":29.0,"low":28.0,"close":0.0},{"date":"1689582892","open":0.0,"high":29.0,"low":28.0,"close":0.0},{"date":"1689583792","open":0.0,"high":29.0,"low":28.0,"close":0.0},{"date":"1689584692","open":0.0,"high":29.0,"low":28.0,"close":0.0},{"date":"1689585592","open":0.0,"high":29.0,"low":28.0,"close":0.0},{"date":"1689586492","open":0.0,"high":29.0,"low":28.0,"close":0.0},{"date":"1689587392","open":0.0,"high":29.0,"low":27.0,"close":0.0},{"date":"1689588292","open":0.0,"high":29.0,"low":27.0,"close":0.0},{"date":"1689589192","open":0.0,"high":29.0,"low":27.0,"close":0.0},{"date":"1689590092","open":0.0,"high":29.0,"low":27.0,"close":0.0},{"date":"1689590992","open":0.0,"high":29.0,"low":28.0,"close":0.0},{"date":"1689591892","open":0.0,"high":29.0,"low":28.0,"close":0.0},{"date":"1689592792","open":0.0,"high":29.0,"low":28.0,"close":0.0},{"date":"1689593692","open":0.0,"high":29.0,"low":28.0,"close":0.0},{"date":"1689594592","open":0.0,"high":29.0,"low":28.0,"close":0.0},{"date":"1689595492","open":0.0,"high":29.0,"low":28.0,"close":0.0},{"date":"1689596392","open":0.0,"high":29.0,"low":28.0,"close":0.0},{"date":"1689597292","open":0.0,"high":29.0,"low":28.0,"close":0.0},{"date":"1689598192","open":0.0,"high":29.0,"low":28.0,"close":0.0},{"date":"1689599092","open":0.0,"high":29.0,"low":28.0,"close":0.0},{"date":"1689599992","open":0.0,"high":29.0,"low":28.0,"close":0.0},{"date":"1689600892","open":0.0,"high":29.0,"low":28.0,"close":0.0},{"date":"1689601792","open":0.0,"high":29.0,"low":28.0,"close":0.0},{"date":"1689602692","open":0.0,"high":29.0,"low":28.0,"close":0.0},{"date":"1689603592","open":0.0,"high":29.0,"low":28.0,"close":0.0},{"date":"1689604492","open":0.0,"high":29.0,"low":28.0,"close":0.0},{"date":"1689605392","open":0.0,"high":29.0,"low":28.0,"close":0.0},{"date":"1689606292","open":0.0,"high":29.0,"low":28.0,"close":0.0},{"date":"1689607192","open":0.0,"high":29.0,"low":28.0,"close":0.0},{"date":"1689608092","open":0.0,"high":29.0,"low":28.0,"close":0.0},{"date":"1689608992","open":0.0,"high":29.0,"low":28.0,"close":0.0},{"date":"1689609892","open":0.0,"high":29.0,"low":28.0,"close":0.0},{"date":"1689610792","open":0.0,"high":29.0,"low":28.0,"close":0.0},{"date":"1689611692","open":0.0,"high":29.0,"low":28.0,"close":0.0},{"date":"1689612592","open":0.0,"high":29.0,"low":28.0,"close":0.0},{"date":"1689613492","open":0.0,"high":29.0,"low":28.0,"close":0.0},{"date":"1689614392","open":0.0,"high":29.0,"low":28.0,"close":0.0},{"date":"1689615292","open":0.0,"high":29.0,"low":28.0,"close":0.0},{"date":"1689616192","open":0.0,"high":29.0,"low":28.0,"close":0.0},{"date":"1689617092","open":0.0,"high":29.0,"low":28.0,"close":0.0},{"date":"1689617992","open":0.0,"high":29.0,"low":28.0,"close":0.0},{"date":"1689618892","open":0.0,"high":29.0,"low":28.0,"close":0.0},{"date":"1689619792","open":0.0,"high":29.0,"low":28.0,"close":0.0},{"date":"1689620692","open":0.0,"high":29.0,"low":28.0,"close":0.0},{"date":"1689621592","open":0.0,"high":29.0,"low":28.0,"close":0.0},{"date":"1689622492","open":0.0,"high":29.0,"low":28.0,"close":0.0},{"date":"1689623392","open":0.0,"high":29.0,"low":28.0,"close":0.0},{"date":"1689624292","open":0.0,"high":29.0,"low":28.0,"close":0.0},{"date":"1689625192","open":0.0,"high":29.0,"low":28.0,"close":0.0},{"date":"1689626092","open":0.0,"high":29.0,"low":28.0,"close":0.0},{"date":"1689626992","open":0.0,"high":29.0,"low":28.0,"close":0.0},{"date":"1689627892","open":0.0,"high":29.0,"low":28.0,"close":0.0},{"date":"1689628792","open":0.0,"high":29.0,"low":28.0,"close":0.0},{"date":"1689629692","open":0.0,"high":29.0,"low":28.0,"close":0.0},{"date":"1689630592","open":0.0,"high":29.0,"low":28.0,"close":0.0},{"date":"1689631492","open":0.0,"high":29.0,"low":28.0,"close":0.0},{"date":"1689632392","open":0.0,"high":29.0,"low":28.0,"close":0.0},{"date":"1689633292","open":0.0,"high":29.0,"low":28.0,"close":0.0},{"date":"1689634192","open":0.0,"high":29.0,"low":28.0,"close":0.0},{"date":"1689635092","open":0.0,"high":29.0,"low":28.0,"close":0.0},{"date":"1689635992","open":0.0,"high":29.0,"low":28.0,"close":0.0},{"date":"1689636892","open":0.0,"high":29.0,"low":28.0,"close":0.0}]